tree_sitter_yarnlock-0.2.0.dist-info/RECORD
tree_sitter_yarnlock-0.2.0.dist-info/WHEEL
tree_sitter_yarnlock-0.2.0.dist-info/top_level.txt
tree_sitter_yarnlock-0.2.0.dist-info/METADATA
tree_sitter_yarnlock/__init__.pyi
tree_sitter_yarnlock/binding.c
tree_sitter_yarnlock/__init__.py
tree_sitter_yarnlock/py.typed
tree_sitter_yarnlock/_binding.abi3.so
