Metadata-Version: 2.1
Name: tree-sitter-yarnlock
Version: 0.2.0
Summary: Yarnlock grammar for tree-sitter
Author-email: Amaan Qureshi <amaanq12@gmail.com>
License: MIT
Project-URL: Homepage, https://github.com/amaanq/tree-sitter-yarnlock
Keywords: incremental,parsing,tree-sitter,yarnlock
Classifier: Intended Audience :: Developers
Classifier: Topic :: Software Development :: Compilers
Classifier: Topic :: Text Processing :: Linguistic
Classifier: Typing :: Typed
Requires-Python: >=3.9
Provides-Extra: core
Requires-Dist: tree-sitter~=0.22; extra == "core"
